whitedot/.DS_Store
whitedot/__init__.py
whitedot/cli.py
whitedot-1.7.6.dist-info/METADATA
whitedot-1.7.6.dist-info/WHEEL
whitedot-1.7.6.dist-info/entry_points.txt
whitedot-1.7.6.dist-info/RECORD
